README.md
setup.py
fdroid_mirror_monitor/__init__.py
fdroid_mirror_monitor/__main__.py
fdroid_mirror_monitor/history.py
fdroid_mirror_monitor/main.py
fdroid_mirror_monitor/mirror.py
fdroid_mirror_monitor/repo.py
fdroid_mirror_monitor/utils.py
fdroid_mirror_monitor/website.py
fdroid_mirror_monitor.egg-info/PKG-INFO
fdroid_mirror_monitor.egg-info/SOURCES.txt
fdroid_mirror_monitor.egg-info/dependency_links.txt
fdroid_mirror_monitor.egg-info/not-zip-safe
fdroid_mirror_monitor.egg-info/requires.txt
fdroid_mirror_monitor.egg-info/top_level.txt
templates/base.html
templates/details.html
templates/footer.html
templates/index.html