Metadata-Version: 2.1
Name: fdroid-mirror-monitor
Version: 0.3.2
Summary: monitoring of known https://f-droid.org mirrors
Home-page: https://gitlab.com/marzzzello/mirror-monitor/
Author: marzzzello
Author-email: 853485-marzzzello@users.noreply.gitlab.com
License: AGPL-3.0
Platform: UNKNOWN
Classifier: Development Status :: 3 - Alpha
Classifier: Intended Audience :: System Administrators
Classifier: Intended Audience :: Telecommunications Industry
Classifier: License :: OSI Approved :: GNU Affero General Public License v3 or later (AGPLv3+)
Classifier: Programming Language :: Python :: 3 :: Only
Classifier: Topic :: System :: Archiving :: Mirroring
Classifier: Topic :: System :: Archiving :: Packaging
Classifier: Topic :: System :: Networking :: Monitoring
Requires-Python: >=3.8
Provides-Extra: tests
